{
  "id": "crafts/bookshelf",
  "kind": "PROJECT",
  "name": "Bookshelf",
  "description": "A simple wooden bookshelf made from planks and screws.",
  "relations": {
    "hasMaterials": [
      {
        "target": "crafts/plank",
        "type": "Material"
      },
      {
        "target": "crafts/screw",
        "type": "Material"
      },
      {
        "target": "crafts/sandpaper",
        "type": "Material"
      },
      {
        "target": "crafts/paint",
        "type": "Material"
      }
    ],
    "hasSteps": [
      "crafts/measure_and_mark",
      "crafts/cut_wood",
      "crafts/sand_surface",
      "crafts/drill_holes",
      "crafts/join_pieces",
      "crafts/apply_paint"
    ],
    "hasParent": [
      {
        "target": "crafts/project"
      }
    ],
    "isA": "woodworking project",
    "produces": [
      {
        "target": "crafts/measure_and_mark"
      },
      {
        "target": "crafts/cut_wood"
      },
      {
        "target": "crafts/sand_surface"
      },
      {
        "target": "crafts/drill_holes"
      },
      {
        "target": "crafts/join_pieces"
      },
      {
        "target": "crafts/apply_paint"
      }
    ]
  },
  "keywords": [
    "bookshelf",
    "book shelf",
    "shelf"
  ]
}
